syscolors/__init__.py
syscolors/rgbColors.py
syscolors/sysColors.py
syscolors-0.0.5.dist-info/LICENCE
syscolors-0.0.5.dist-info/METADATA
syscolors-0.0.5.dist-info/WHEEL
syscolors-0.0.5.dist-info/top_level.txt
syscolors-0.0.5.dist-info/RECORD
