Metadata-Version: 2.1
Name: syscolors
Version: 0.0.5
Summary: Color your Python terminal screen as you wish.
Home-page: https://github.com/IMaresaLI/syscolors
Author: Batuhan Olgac
Author-email: mares4l@hotmail.com
License: UNKNOWN
Project-URL: Bug Tracker, https://github.com/IMaresaLI/syscolors/issues
Platform: UNKNOWN
Classifier: Programming Language :: Python :: 2.7
Classifier: Programming Language :: Python :: 3
Classifier: Programming Language :: Python :: 3.6
Classifier: Programming Language :: Python :: 3.7
Classifier: Programming Language :: Python :: 3.8
Classifier: Programming Language :: Python :: 3.9
Classifier: License :: OSI Approved :: MIT License
Classifier: Operating System :: OS Independent
Classifier: Operating System :: Unix
Classifier: Operating System :: POSIX
Classifier: Operating System :: Microsoft :: Windows
Requires-Python: >=2.7
License-File: LICENCE
